raveboard/__init__.py
raveboard/__main__.py
raveboard/ui_context.py
raveboard/ui_model.py
raveboard/dist/ravestate/3rdpartylicenses.txt
raveboard/dist/ravestate/favicon.ico
raveboard/dist/ravestate/index.html
raveboard/dist/ravestate/main.e5cf80332fe66f7c26b7.js
raveboard/dist/ravestate/polyfills.e1875cc5fa822646a076.js
raveboard/dist/ravestate/runtime.858f8dd898b75fe86926.js
raveboard/dist/ravestate/styles.c44424ccd104973d43ff.css
ravestate/__init__.py
ravestate/__main__.py
ravestate/activation.py
ravestate/argparser.py
ravestate/causal.py
ravestate/config.py
ravestate/constraint.py
ravestate/consumable.py
ravestate/context.py
ravestate/iactivation.py
ravestate/icontext.py
ravestate/module.py
ravestate/property.py
ravestate/receptor.py
ravestate/spike.py
ravestate/state.py
ravestate/testfixtures.py
ravestate/threadlocal.py
ravestate/wrappers.py
ravestate_akinator/__init__.py
ravestate_akinator/api.py
ravestate_conio/__init__.py
ravestate_emotion/__init__.py
ravestate_fillers/__init__.py
ravestate_genqa/__init__.py
ravestate_hibye/__init__.py
ravestate_idle/__init__.py
ravestate_interloc/__init__.py
ravestate_nlp/__init__.py
ravestate_nlp/extract_triples.py
ravestate_nlp/question_word.py
ravestate_nlp/triple.py
ravestate_nlp/triple_match_result.py
ravestate_nlp/yes_no.py
ravestate_ontology/__init__.py
ravestate_ontology/dummy_session.py
ravestate_ontology/ravestate_ontology.yml
ravestate_persqa/__init__.py
ravestate_persqa/persqa_phrases/QAList.yml
ravestate_phrases_basic_en/__init__.py
ravestate_phrases_basic_en/en/answer.yml
ravestate_phrases_basic_en/en/avoid.yml
ravestate_phrases_basic_en/en/consent.yml
ravestate_phrases_basic_en/en/distract.yml
ravestate_phrases_basic_en/en/facts.yml
ravestate_phrases_basic_en/en/farewell.yml
ravestate_phrases_basic_en/en/fillers.yml
ravestate_phrases_basic_en/en/flattery.yml
ravestate_phrases_basic_en/en/greeting.yml
ravestate_phrases_basic_en/en/joke.yml
ravestate_phrases_basic_en/en/offer-fact.yml
ravestate-0.7.0.post1.dist-info/LICENSE
ravestate-0.7.0.post1.dist-info/METADATA
ravestate-0.7.0.post1.dist-info/WHEEL
ravestate-0.7.0.post1.dist-info/top_level.txt
ravestate-0.7.0.post1.dist-info/RECORD
