Metadata-Version: 2.1
Name: ravestate
Version: 0.7.0.post1
Summary: Ravestate is a reactive library for real-time natural language dialog systems.
Home-page: https://github.com/roboy/ravestate
Author: Roboy
Author-email: info@roboy.org
License: UNKNOWN
Platform: UNKNOWN
Classifier: Programming Language :: Python :: 3
Classifier: Operating System :: OS Independent
Requires-Python: >=3.6
Requires-Dist: unidecode
Requires-Dist: argparse
Requires-Dist: pyyaml (>=5.1)
Requires-Dist: python-telegram-bot
Requires-Dist: pyyaml-include
Requires-Dist: roboy-parlai (>=0.1.post3)
Requires-Dist: spacy (==2.1.0)
Requires-Dist: flask
Requires-Dist: flask-socketio
Requires-Dist: requests
Requires-Dist: scientio (>=0.9.1rc2)
Requires-Dist: redis
Requires-Dist: face-recognition
Requires-Dist: numpy
Requires-Dist: pytorch-pretrained-bert
Requires-Dist: pytorch-transformers
Requires-Dist: python-socketio
Requires-Dist: reggol (>=0.2.0)
